assistancechat/__init__.py
assistancechat/__main__.py
assistancechat/config.py
assistancechat/conversations.py
assistancechat/main.py
assistancechat-0.1.0.dist-info/METADATA
assistancechat-0.1.0.dist-info/WHEEL
assistancechat-0.1.0.dist-info/RECORD
