Metadata-Version: 2.1
Name: assistancechat
Version: 0.1.0
Summary: 
License: Apache-2.0
Author: Simon Biggs
Author-email: simon.biggs@radiotherapy.ai
Requires-Python: >=3.10,<4.0
Classifier: License :: OSI Approved :: Apache Software License
Classifier: Programming Language :: Python :: 3
Classifier: Programming Language :: Python :: 3.10
Classifier: Programming Language :: Python :: 3.11
Requires-Dist: fastapi (>=0.88.0,<0.89.0)
Requires-Dist: keyring (>=23.13.1,<24.0.0)
Requires-Dist: openai (>=0.25.0,<0.26.0)
Requires-Dist: uvicorn[standard] (>=0.20.0,<0.21.0)
